[{"ver":1,"sampleRate":100,"tags":{"ai.device.id":"","ai.cloud.roleInstance":"DESKTOP-OI3TIMR","ai.device.osVersion":"Windows_NT 10.0.26100","ai.cloud.role":"Web","ai.device.osArchitecture":"x64","ai.device.osPlatform":"win32","ai.internal.sdkVersion":"uwm_node:2.9.8"},"data":{"baseType":"MetricData","baseData":{"ver":2,"metrics":[{"kind":1,"count":1,"max":24.306188146358956,"min":24.306188146358956,"name":"\\Processor(_Total)\\% Processor Time","stdDev":0,"value":24.306188146358956}],"properties":{}}},"iKey":"b73649cf-ca8f-4768-9e0e-b789d8529db5","name":"Microsoft.ApplicationInsights.b73649cfca8f47689e0eb789d8529db5.Metric","time":"2025-11-19T17:16:39.377Z"},{"ver":1,"sampleRate":100,"tags":{"ai.device.id":"","ai.cloud.roleInstance":"DESKTOP-OI3TIMR","ai.device.osVersion":"Windows_NT 10.0.26100","ai.cloud.role":"Web","ai.device.osArchitecture":"x64","ai.device.osPlatform":"win32","ai.internal.sdkVersion":"uwm_node:2.9.8"},"data":{"baseType":"MetricData","baseData":{"ver":2,"metrics":[{"kind":1,"count":1,"max":0.012916311855579994,"min":0.012916311855579994,"name":"\\Process(??APP_WIN32_PROC??)\\% Processor Time","stdDev":0,"value":0.012916311855579994}],"properties":{}}},"iKey":"b73649cf-ca8f-4768-9e0e-b789d8529db5","name":"Microsoft.ApplicationInsights.b73649cfca8f47689e0eb789d8529db5.Metric","time":"2025-11-19T17:16:39.377Z"},{"ver":1,"sampleRate":100,"tags":{"ai.device.id":"","ai.cloud.roleInstance":"DESKTOP-OI3TIMR","ai.device.osVersion":"Windows_NT 10.0.26100","ai.cloud.role":"Web","ai.device.osArchitecture":"x64","ai.device.osPlatform":"win32","ai.internal.sdkVersion":"uwm_node:2.9.8"},"data":{"baseType":"MetricData","baseData":{"ver":2,"metrics":[{"kind":1,"count":1,"max":120188928,"min":120188928,"name":"\\Process(??APP_WIN32_PROC??)\\Private Bytes","stdDev":0,"value":120188928}],"properties":{}}},"iKey":"b73649cf-ca8f-4768-9e0e-b789d8529db5","name":"Microsoft.ApplicationInsights.b73649cfca8f47689e0eb789d8529db5.Metric","time":"2025-11-19T17:16:39.378Z"},{"ver":1,"sampleRate":100,"tags":{"ai.device.id":"","ai.cloud.roleInstance":"DESKTOP-OI3TIMR","ai.device.osVersion":"Windows_NT 10.0.26100","ai.cloud.role":"Web","ai.device.osArchitecture":"x64","ai.device.osPlatform":"win32","ai.internal.sdkVersion":"uwm_node:2.9.8"},"data":{"baseType":"MetricData","baseData":{"ver":2,"metrics":[{"kind":1,"count":1,"max":7197319168,"min":7197319168,"name":"\\Memory\\Available Bytes","stdDev":0,"value":7197319168}],"properties":{}}},"iKey":"b73649cf-ca8f-4768-9e0e-b789d8529db5","name":"Microsoft.ApplicationInsights.b73649cfca8f47689e0eb789d8529db5.Metric","time":"2025-11-19T17:16:39.378Z"},{"ver":1,"sampleRate":100,"tags":{"ai.device.id":"","ai.cloud.roleInstance":"DESKTOP-OI3TIMR","ai.device.osVersion":"Windows_NT 10.0.26100","ai.cloud.role":"Web","ai.device.osArchitecture":"x64","ai.device.osPlatform":"win32","ai.internal.sdkVersion":"uwm_node:2.9.8"},"data":{"baseType":"MetricData","baseData":{"ver":2,"metrics":[{"kind":1,"count":1,"max":0,"min":0,"name":"\\ASP.NET Applications(??APP_W3SVC_PROC??)\\Requests/Sec","stdDev":0,"value":0}],"properties":{}}},"iKey":"b73649cf-ca8f-4768-9e0e-b789d8529db5","name":"Microsoft.ApplicationInsights.b73649cfca8f47689e0eb789d8529db5.Metric","time":"2025-11-19T17:16:39.378Z"},{"ver":1,"sampleRate":100,"tags":{"ai.device.id":"","ai.cloud.roleInstance":"DESKTOP-OI3TIMR","ai.device.osVersion":"Windows_NT 10.0.26100","ai.cloud.role":"Web","ai.device.osArchitecture":"x64","ai.device.osPlatform":"win32","ai.internal.sdkVersion":"uwm_node:2.9.8"},"data":{"baseType":"MetricData","baseData":{"ver":2,"metrics":[{"kind":1,"count":1,"max":0,"min":0,"name":"\\ASP.NET Applications(??APP_W3SVC_PROC??)\\Request Execution Time","stdDev":0,"value":0}],"properties":{}}},"iKey":"b73649cf-ca8f-4768-9e0e-b789d8529db5","name":"Microsoft.ApplicationInsights.b73649cfca8f47689e0eb789d8529db5.Metric","time":"2025-11-19T17:16:39.378Z"}]